LICENSE
MANIFEST.in
README.rst
distribute_setup.py
setup.py
atp/__init__.py
atp/concurrency.py
atp/excepts.py
atp/mixin.py
atp/version.py
atp.egg-info/PKG-INFO
atp.egg-info/SOURCES.txt
atp.egg-info/dependency_links.txt
atp.egg-info/top_level.txt
atp/test/__init__.py
atp/test/test_concurrency.py
atp/test/test_mixin.py