Metadata-Version: 1.1
Name: atp
Version: 0.1.0
Summary: An adaptive thread pool implementation
Home-page: https://github.com/amrali/atp
Author: Amr Ali
Author-email: amr.ali.cc@gmail.com
License: GPLv3+
Platform: Posix
Classifier: License :: OSI Approved :: GNU General Public License v3 or later (GPLv3+)
Classifier: Operating System :: OS Independent
Classifier: Programming Language :: Python
Classifier: Natural Language :: English
Classifier: Intended Audience :: Developers
Classifier: Intended Audience :: Information Technology
Classifier: Programming Language :: Python :: 2
Classifier: Programming Language :: Python :: 2.7
